K07VN_Crypto/Crypto.py
K07VN_Crypto/__init__.py
K07VN_Crypto/__version__.py
K07VN_Crypto-1.0.5.dist-info/METADATA
K07VN_Crypto-1.0.5.dist-info/WHEEL
K07VN_Crypto-1.0.5.dist-info/top_level.txt
K07VN_Crypto-1.0.5.dist-info/RECORD
