Metadata-Version: 2.1
Name: K07VN-Crypto
Version: 1.0.5
Summary: Bạn là 1 nhà phát triển phần mềm, công cụ ?
Home-page: https://github.com/tnk-admin/K07VN_Crypto
Author: K07VN
Author-email: khanhnekyh2007@gmail.com
Keywords: python,crypto,encode,K07VN_Crypto,string,pycryptodomex
Classifier: License :: OSI Approved :: GNU General Public License v3 (GPLv3)
Classifier: Programming Language :: Python :: 3.7
Classifier: Programming Language :: Python :: 3.8
Classifier: Programming Language :: Python :: 3.9
Classifier: Programming Language :: Python :: 3.10
Classifier: Programming Language :: Python :: 3.11
Classifier: License :: OSI Approved :: MIT License
Classifier: Operating System :: OS Independent
Requires-Python: >=3.6
Requires-Dist: pycryptodome
